{"errors":[],"warnings":[],"namedChunkGroups":{"app":{"chunks":[6,0,5,2],"assets":["webpack-runtime-f96702818d983f7612da.js","styles.3caee45c9345b5d2ee60.css","styles-9b6f388623a2ec93d35f.js","framework-dd95e8b3d258d85252e9.js","app-14e098504f5decebfc30.js"],"children":{},"childAssets":{}},"component---src-pages-contact-js":{"chunks":[0,1,3],"assets":["styles.3caee45c9345b5d2ee60.css","styles-9b6f388623a2ec93d35f.js","commons-4b77eb4df86909383858.js","component---src-pages-contact-js-5e8407164bf7a5a415ab.js"],"children":{},"childAssets":{}},"component---src-pages-index-js":{"chunks":[0,1,4],"assets":["styles.3caee45c9345b5d2ee60.css","styles-9b6f388623a2ec93d35f.js","commons-4b77eb4df86909383858.js","component---src-pages-index-js-d1f18d96d6a55d8ba5db.js"],"children":{},"childAssets":{}}},"assetsByChunkName":{"app":["webpack-runtime-f96702818d983f7612da.js","styles.3caee45c9345b5d2ee60.css","styles-9b6f388623a2ec93d35f.js","framework-dd95e8b3d258d85252e9.js","app-14e098504f5decebfc30.js"],"component---src-pages-contact-js":["styles.3caee45c9345b5d2ee60.css","styles-9b6f388623a2ec93d35f.js","commons-4b77eb4df86909383858.js","component---src-pages-contact-js-5e8407164bf7a5a415ab.js"],"component---src-pages-index-js":["styles.3caee45c9345b5d2ee60.css","styles-9b6f388623a2ec93d35f.js","commons-4b77eb4df86909383858.js","component---src-pages-index-js-d1f18d96d6a55d8ba5db.js"]}}